LICENCE.txt
README.txt
distribute_setup.py
setup.py
works_to_word.py
Works_4x_to_Word_Python_Converter.egg-info/PKG-INFO
Works_4x_to_Word_Python_Converter.egg-info/SOURCES.txt
Works_4x_to_Word_Python_Converter.egg-info/dependency_links.txt
Works_4x_to_Word_Python_Converter.egg-info/requires.txt
Works_4x_to_Word_Python_Converter.egg-info/top_level.txt
works4xtowordpythonconverter/__init__.py
works4xtowordpythonconverter/create.py
works4xtowordpythonconverter/read_works.py