Metadata-Version: 1.0
Name: Works-4x-to-Word-Python-Converter
Version: 2.0.1
Summary: Works 4.x to Word Python Converter bulk converts those ancient archaic Microsoft Works Word Processor 4.x (.wps) files to Microsoft Word 2007 format (.docx).
Home-page: https://code.google.com/p/works-4x-to-word-python-converter/
Author: Nick Wilde
Author-email: nick.wilde.90@gmail.com
License: New BSD
Keywords: Microsoft Works 4x Word Converter
Platform: UNKNOWN
